vpalette/__init__.py
vpalette/colors.py
vpalette/palette.py
vpalette-3.0.0.dist-info/LICENSE.txt
vpalette-3.0.0.dist-info/METADATA
vpalette-3.0.0.dist-info/WHEEL
vpalette-3.0.0.dist-info/RECORD
